{
  "current": {
    "generatedAt": "2026-07-05T00:13:45.265Z",
    "apps": 28,
    "testFiles": 32,
    "testCases": 276,
    "tokenViolations": 0,
    "offSystemUtilities": 0,
    "offSystemStyle": 2,
    "offSystemStyleDims": {
      "radii": 0,
      "type": 0,
      "motion": 2
    },
    "bundleGzKB": 705.4,
    "bundleRawKB": 2403.7
  },
  "history": [
    {
      "generatedAt": "2026-07-03T15:15:18.165Z",
      "apps": 27,
      "testFiles": 29,
      "testCases": 246,
      "tokenViolations": 0,
      "offSystemUtilities": 0,
      "bundleGzKB": null,
      "bundleRawKB": null
    },
    {
      "generatedAt": "2026-07-03T15:18:33.742Z",
      "apps": 27,
      "testFiles": 29,
      "testCases": 246,
      "tokenViolations": 0,
      "offSystemUtilities": 0,
      "bundleGzKB": 701.2,
      "bundleRawKB": 2391.6
    },
    {
      "generatedAt": "2026-07-03T15:22:06.132Z",
      "apps": 27,
      "testFiles": 29,
      "testCases": 246,
      "tokenViolations": 0,
      "offSystemUtilities": 0,
      "bundleGzKB": 701.2,
      "bundleRawKB": 2391.6
    },
    {
      "generatedAt": "2026-07-03T15:24:25.530Z",
      "apps": 27,
      "testFiles": 29,
      "testCases": 246,
      "tokenViolations": 0,
      "offSystemUtilities": 0,
      "bundleGzKB": 701.2,
      "bundleRawKB": 2391.6
    },
    {
      "generatedAt": "2026-07-03T18:08:07.775Z",
      "apps": 27,
      "testFiles": 29,
      "testCases": 246,
      "tokenViolations": 0,
      "offSystemUtilities": 0,
      "bundleGzKB": 701.2,
      "bundleRawKB": 2391.6
    },
    {
      "generatedAt": "2026-07-03T18:08:07.926Z",
      "apps": 27,
      "testFiles": 29,
      "testCases": 246,
      "tokenViolations": 0,
      "offSystemUtilities": 0,
      "bundleGzKB": 701.2,
      "bundleRawKB": 2391.6
    },
    {
      "generatedAt": "2026-07-03T20:16:03.238Z",
      "apps": 27,
      "testFiles": 30,
      "testCases": 250,
      "tokenViolations": 0,
      "offSystemUtilities": 0,
      "bundleGzKB": 701.4,
      "bundleRawKB": 2392.3
    },
    {
      "generatedAt": "2026-07-03T23:10:53.687Z",
      "apps": 27,
      "testFiles": 30,
      "testCases": 250,
      "tokenViolations": 0,
      "offSystemUtilities": 0,
      "bundleGzKB": 701.4,
      "bundleRawKB": 2392.3
    },
    {
      "generatedAt": "2026-07-03T23:10:59.793Z",
      "apps": 27,
      "testFiles": 30,
      "testCases": 250,
      "tokenViolations": 0,
      "offSystemUtilities": 0,
      "bundleGzKB": 701.4,
      "bundleRawKB": 2392.3
    },
    {
      "generatedAt": "2026-07-04T00:16:25.539Z",
      "apps": 28,
      "testFiles": 31,
      "testCases": 265,
      "tokenViolations": 0,
      "offSystemUtilities": 0,
      "bundleGzKB": 703.5,
      "bundleRawKB": 2398
    },
    {
      "generatedAt": "2026-07-04T03:08:51.895Z",
      "apps": 28,
      "testFiles": 31,
      "testCases": 265,
      "tokenViolations": 0,
      "offSystemUtilities": 0,
      "bundleGzKB": 703.5,
      "bundleRawKB": 2398
    },
    {
      "generatedAt": "2026-07-04T05:15:52.753Z",
      "apps": 28,
      "testFiles": 31,
      "testCases": 272,
      "tokenViolations": 0,
      "offSystemUtilities": 0,
      "bundleGzKB": 704.8,
      "bundleRawKB": 2401.4
    },
    {
      "generatedAt": "2026-07-04T08:08:44.480Z",
      "apps": 28,
      "testFiles": 31,
      "testCases": 272,
      "tokenViolations": 0,
      "offSystemUtilities": 0,
      "bundleGzKB": 704.8,
      "bundleRawKB": 2401.4
    },
    {
      "generatedAt": "2026-07-04T08:11:31.824Z",
      "apps": 28,
      "testFiles": 31,
      "testCases": 272,
      "tokenViolations": 0,
      "offSystemUtilities": 0,
      "bundleGzKB": 704.8,
      "bundleRawKB": 2401.4
    },
    {
      "generatedAt": "2026-07-04T10:14:08.297Z",
      "apps": 28,
      "testFiles": 32,
      "testCases": 276,
      "tokenViolations": 0,
      "offSystemUtilities": 0,
      "bundleGzKB": 705.3,
      "bundleRawKB": 2402.9
    },
    {
      "generatedAt": "2026-07-04T13:08:33.712Z",
      "apps": 28,
      "testFiles": 32,
      "testCases": 276,
      "tokenViolations": 0,
      "offSystemUtilities": 0,
      "bundleGzKB": 705.4,
      "bundleRawKB": 2403
    },
    {
      "generatedAt": "2026-07-04T18:08:51.077Z",
      "apps": 28,
      "testFiles": 32,
      "testCases": 276,
      "tokenViolations": 0,
      "offSystemUtilities": 0,
      "bundleGzKB": 705.4,
      "bundleRawKB": 2403
    },
    {
      "generatedAt": "2026-07-04T18:41:24.149Z",
      "apps": 28,
      "testFiles": 32,
      "testCases": 276,
      "tokenViolations": 0,
      "offSystemUtilities": 0,
      "offSystemStyle": 56,
      "offSystemStyleDims": {
        "radii": 12,
        "type": 42,
        "motion": 2
      },
      "bundleGzKB": 705.4,
      "bundleRawKB": 2403.1
    },
    {
      "generatedAt": "2026-07-04T18:44:39.253Z",
      "apps": 28,
      "testFiles": 32,
      "testCases": 276,
      "tokenViolations": 0,
      "offSystemUtilities": 0,
      "offSystemStyle": 56,
      "offSystemStyleDims": {
        "radii": 12,
        "type": 42,
        "motion": 2
      },
      "bundleGzKB": 705.4,
      "bundleRawKB": 2403.1
    },
    {
      "generatedAt": "2026-07-04T23:09:07.726Z",
      "apps": 28,
      "testFiles": 32,
      "testCases": 276,
      "tokenViolations": 0,
      "offSystemUtilities": 0,
      "offSystemStyle": 56,
      "offSystemStyleDims": {
        "radii": 12,
        "type": 42,
        "motion": 2
      },
      "bundleGzKB": 705.4,
      "bundleRawKB": 2403.1
    },
    {
      "generatedAt": "2026-07-04T23:09:07.912Z",
      "apps": 28,
      "testFiles": 32,
      "testCases": 276,
      "tokenViolations": 0,
      "offSystemUtilities": 0,
      "offSystemStyle": 56,
      "offSystemStyleDims": {
        "radii": 12,
        "type": 42,
        "motion": 2
      },
      "bundleGzKB": 705.4,
      "bundleRawKB": 2403.1
    },
    {
      "generatedAt": "2026-07-04T23:52:34.311Z",
      "apps": 28,
      "testFiles": 32,
      "testCases": 276,
      "tokenViolations": 0,
      "offSystemUtilities": 0,
      "offSystemStyle": 56,
      "offSystemStyleDims": {
        "radii": 12,
        "type": 42,
        "motion": 2
      },
      "bundleGzKB": 705.4,
      "bundleRawKB": 2403.1
    },
    {
      "generatedAt": "2026-07-04T23:55:29.098Z",
      "apps": 28,
      "testFiles": 32,
      "testCases": 276,
      "tokenViolations": 0,
      "offSystemUtilities": 0,
      "offSystemStyle": 14,
      "offSystemStyleDims": {
        "radii": 12,
        "type": 0,
        "motion": 2
      },
      "bundleGzKB": 705.4,
      "bundleRawKB": 2403.1
    },
    {
      "generatedAt": "2026-07-04T23:56:13.298Z",
      "apps": 28,
      "testFiles": 32,
      "testCases": 276,
      "tokenViolations": 0,
      "offSystemUtilities": 0,
      "offSystemStyle": 14,
      "offSystemStyleDims": {
        "radii": 12,
        "type": 0,
        "motion": 2
      },
      "bundleGzKB": 705.4,
      "bundleRawKB": 2403.5
    },
    {
      "generatedAt": "2026-07-04T23:56:26.119Z",
      "apps": 28,
      "testFiles": 32,
      "testCases": 276,
      "tokenViolations": 0,
      "offSystemUtilities": 0,
      "offSystemStyle": 14,
      "offSystemStyleDims": {
        "radii": 12,
        "type": 0,
        "motion": 2
      },
      "bundleGzKB": 705.4,
      "bundleRawKB": 2403.5
    },
    {
      "generatedAt": "2026-07-04T23:59:11.444Z",
      "apps": 28,
      "testFiles": 32,
      "testCases": 276,
      "tokenViolations": 0,
      "offSystemUtilities": 0,
      "offSystemStyle": 14,
      "offSystemStyleDims": {
        "radii": 12,
        "type": 0,
        "motion": 2
      },
      "bundleGzKB": 705.4,
      "bundleRawKB": 2403.5
    },
    {
      "generatedAt": "2026-07-04T23:59:11.589Z",
      "apps": 28,
      "testFiles": 32,
      "testCases": 276,
      "tokenViolations": 0,
      "offSystemUtilities": 0,
      "offSystemStyle": 14,
      "offSystemStyleDims": {
        "radii": 12,
        "type": 0,
        "motion": 2
      },
      "bundleGzKB": 705.4,
      "bundleRawKB": 2403.5
    },
    {
      "generatedAt": "2026-07-05T00:10:44.732Z",
      "apps": 28,
      "testFiles": 32,
      "testCases": 276,
      "tokenViolations": 0,
      "offSystemUtilities": 0,
      "offSystemStyle": 14,
      "offSystemStyleDims": {
        "radii": 12,
        "type": 0,
        "motion": 2
      },
      "bundleGzKB": null,
      "bundleRawKB": null
    },
    {
      "generatedAt": "2026-07-05T00:12:47.795Z",
      "apps": 28,
      "testFiles": 32,
      "testCases": 276,
      "tokenViolations": 0,
      "offSystemUtilities": 0,
      "offSystemStyle": 2,
      "offSystemStyleDims": {
        "radii": 0,
        "type": 0,
        "motion": 2
      },
      "bundleGzKB": null,
      "bundleRawKB": null
    },
    {
      "generatedAt": "2026-07-05T00:13:45.084Z",
      "apps": 28,
      "testFiles": 32,
      "testCases": 276,
      "tokenViolations": 0,
      "offSystemUtilities": 0,
      "offSystemStyle": 2,
      "offSystemStyleDims": {
        "radii": 0,
        "type": 0,
        "motion": 2
      },
      "bundleGzKB": 705.4,
      "bundleRawKB": 2403.7
    }
  ]
}
